riff/__init__.py
riff/logger.py
riff/riff.py
riff/utils.py
riff/violation.py
riff-0.0.287.0.dist-info/LICENSE.md
riff-0.0.287.0.dist-info/METADATA
riff-0.0.287.0.dist-info/WHEEL
riff-0.0.287.0.dist-info/entry_points.txt
riff-0.0.287.0.dist-info/RECORD
