Metadata-Version: 2.1
Name: riff
Version: 0.0.287.0
Summary: Run ruff, but only fail on modified lines.
License: MIT
Author: dorschw
Author-email: 81086590+dorschw@users.noreply.github.com
Requires-Python: >=3.10,<4.0
Classifier: License :: OSI Approved :: MIT License
Classifier: Programming Language :: Python :: 3
Classifier: Programming Language :: Python :: 3.10
Classifier: Programming Language :: Python :: 3.11
Requires-Dist: gitpython (>=3.1.27,<4.0.0)
Requires-Dist: loguru (>=0.7.0,<0.8.0)
Requires-Dist: ruff (==0.0.287)
Requires-Dist: typer (>=0.7.0)
Requires-Dist: unidiff (>=0.7.5,<0.8.0)
Project-URL: Bug Tracker, https://github.com/dorschw/riff/issues
Project-URL: Homepage, https://github.com/dorschw/riff
Project-URL: Source, https://github.com/dorschw/riff
